Workbook

Sheet Summary
A3: Rótulos de Linha | B3: Project Type | C3: Resource Name | D3: FunnelID | E3: CostRate (w/ Taxes) | F3: Soma de Time Actual | G3: Soma de Total Cost
A4: Sietech | B4: FF | C4: Nelson Simoes | D4: 406-VCK498 | E4: 173.00275 | F4: 3 | G4: 519.00826
D5: 434-VCK448 | E5: 173.00275 | F5: 3 | G5: 519.00826
D6: 448-VCK494 | E6: 173.00275 | F6: 1 | G6: 173.00275
D7: A7lAPT28665 | E7: 173.00275 | F7: 12 | G7: 2076.0331
B8: FF Total | F8: 19 | G8: 3287.0523 | H8: BRP2184
B9: NB | C9: Nelson Simoes | D9: NB-Consultoria-Tec&Dev | E9: 110 | F9: 123 | G9: 13530
D10: NBP-PE-PLAN10 | E10: 110 | F10: 20 | G10: 2200
D11: NBP-PE-PLAN12 | E11: 110 | F11: 6 | G11: 660
D12: NBP-PE-PLAN23 | E12: 173.00275 | F12: 4 | G12: 692.01102
D13: NB-Scrum-Dev | E13: 95.239669 | F13: 4 | G13: 380.95868
B14: NB Total | F14: 157 | G14: 17462.97 | H14: BRP2185
A15: Sietech Total | F15: 176 | G15: 20750.022
A16: Total Geral | F16: 176 | G16: 20750.022

Sheet Agosto 2024
A1: FunnelID | B1: Work Date | C1: Date TimeSheet | D1: CCID | E1: Year | F1: Month | G1: Day | H1: Week | I1: Time Actual | J1: Company | K1: Resource Name | L1: Role | M1: Comments | N1: CostRate | O1: CostRate (w/ Taxes) | P1: Total Cost | Q1: BillingRate | R1: BillingRate w/ Taxes | S1: Total Revenue | T1: Customer Name | U1: Project Type
A2: 434-VCK448 | B2: 45525 | C2: 45538 | D2: SOW | E2: 2024 | F2: 8 | G2: 21 | H2: 34 | I2: 1 | J2: Sietech | K2: Nelson Simoes | L2: Project Manager | M2: Alinhamento de merges com equipe de desenvolvimento no projeto de conversão. | N2: 157 | O2: =ApprovedTimeReport_001_202485[[#This Row],[CostRate]]/0.9075 -> 173.00275 | P2: =ApprovedTimeReport_001_202485[[#This Row],[CostRate (w/ Taxes)]]*ApprovedTimeReport_001_202485[[#This Row],[Time Actual]] -> 173.00275 | Q2: 210.66 | R2: =ApprovedTimeReport_001_202485[[#This Row],[BillingRate]]/0.8785 -> 239.79511 | S2: =ApprovedTimeReport_001_202485[[#This Row],[BillingRate w/ Taxes]]*ApprovedTimeReport_001_202485[[#This Row],[Time Actual]] -> 239.79511 | T2: AMVAC do Brasil Representacoes | U2: =VLOOKUP(A:A,Vlookup!A:B,2,0) -> FF
A3: 434-VCK448 | B3: 45520 | C3: 45538 | D3: SOW | E3: 2024 | F3: 8 | G3: 16 | H3: 33 | I3: 2 | J3: Sietech | K3: Nelson Simoes | L3: Project Manager | M3: Tratamento de demandas do BPO e alinhamento com projetos para atuação de DEV no upgrade. | N3: 157 | O3: =ApprovedTimeReport_001_202485[[#This Row],[CostRate]]/0.9075 -> 173.00275 | P3: =ApprovedTimeReport_001_202485[[#This Row],[CostRate (w/ Taxes)]]*ApprovedTimeReport_001_202485[[#This Row],[Time Actual]] -> 346.00551 | Q3: 210.66 | R3: =ApprovedTimeReport_001_202485[[#This Row],[BillingRate]]/0.8785 -> 239.79511 | S3: =ApprovedTimeReport_001_202485[[#This Row],[BillingRate w/ Taxes]]*ApprovedTimeReport_001_202485[[#This Row],[Time Actual]] -> 479.59021 | T3: AMVAC do Brasil Representacoes | U3: =VLOOKUP(A:A,Vlookup!A:B,2,0) -> FF
A4: A7lAPT28665 | B4: 45518 | C4: 45538 | D4: CO05 | E4: 2024 | F4: 8 | G4: 14 | H4: 33 | I4: 2 | J4: Sietech | K4: Nelson Simoes | L4: Project Manager | M4: Tratamento de demandas OD-362, 268, 437, 406, 354, 430, 428 | N4: 157 | O4: =ApprovedTimeReport_001_202485[[#This Row],[CostRate]]/0.9075 -> 173.00275 | P4: =ApprovedTimeReport_001_202485[[#This Row],[CostRate (w/ Taxes)]]*ApprovedTimeReport_001_202485[[#This Row],[Time Actual]] -> 346.00551 | Q4: 199 | R4: =ApprovedTimeReport_001_202485[[#This Row],[BillingRate]]/0.8785 -> 226.52248 | S4: =ApprovedTimeReport_001_202485[[#This Row],[BillingRate w/ Taxes]]*ApprovedTimeReport_001_202485[[#This Row],[Time Actual]] -> 453.04496 | T4: APTIV Man e Serv de Distr. Ltda | U4: =VLOOKUP(A:A,Vlookup!A:B,2,0) -> FF
A5: A7lAPT28665 | B5: 45516 | C5: 45538 | D5: CO05 | E5: 2024 | F5: 8 | G5: 12 | H5: 33 | I5: 8 | J5: Sietech | K5: Nelson Simoes | L5: Project Manager | M5: Revisão de atividades da sprint 12, escalonamento Aptiv | N5: 157 | O5: =ApprovedTimeReport_001_202485[[#This Row],[CostRate]]/0.9075 -> 173.00275 | P5: =ApprovedTimeReport_001_202485[[#This Row],[CostRate (w/ Taxes)]]*ApprovedTimeReport_001_202485[[#This Row],[Time Actual]] -> 1384.022 | Q5: 199 | R5: =ApprovedTimeReport_001_202485[[#This Row],[BillingRate]]/0.8785 -> 226.52248 | S5: =ApprovedTimeReport_001_202485[[#This Row],[BillingRate w/ Taxes]]*ApprovedTimeReport_001_202485[[#This Row],[Time Actual]] -> 1812.1799 | T5: APTIV Man e Serv de Distr. Ltda | U5: =VLOOKUP(A:A,Vlookup!A:B,2,0) -> FF
A6: A7lAPT28665 | B6: 45511 | C6: 45538 | D6: CO05 | E6: 2024 | F6: 8 | G6: 7 | H6: 32 | I6: 2 | J6: Sietech | K6: Nelson Simoes | L6: Project Manager | M6: Tratamento de demandas do BPO VBPO 125, 134 | N6: 157 | O6: =ApprovedTimeReport_001_202485[[#This Row],[CostRate]]/0.9075 -> 173.00275 | P6: =ApprovedTimeReport_001_202485[[#This Row],[CostRate (w/ Taxes)]]*ApprovedTimeReport_001_202485[[#This Row],[Time Actual]] -> 346.00551 | Q6: 199 | R6: =ApprovedTimeReport_001_202485[[#This Row],[BillingRate]]/0.8785 -> 226.52248 | S6: =ApprovedTimeReport_001_202485[[#This Row],[BillingRate w/ Taxes]]*ApprovedTimeReport_001_202485[[#This Row],[Time Actual]] -> 453.04496 | T6: APTIV Man e Serv de Distr. Ltda | U6: =VLOOKUP(A:A,Vlookup!A:B,2,0) -> FF
A7: 448-VCK494 | B7: 45524 | C7: 45538 | D7: SOW | E7: 2024 | F7: 8 | G7: 20 | H7: 34 | I7: 1 | J7: Sietech | K7: Nelson Simoes | L7: Program Manager | M7: Follow up de demandas de BPO, revisão de indicadores. | N7: 157 | O7: =ApprovedTimeReport_001_202485[[#This Row],[CostRate]]/0.9075 -> 173.00275 | P7: =ApprovedTimeReport_001_202485[[#This Row],[CostRate (w/ Taxes)]]*ApprovedTimeReport_001_202485[[#This Row],[Time Actual]] -> 173.00275 | Q7: 168.38 | R7: =ApprovedTimeReport_001_202485[[#This Row],[BillingRate]]/0.8785 -> 191.66762 | S7: =ApprovedTimeReport_001_202485[[#This Row],[BillingRate w/ Taxes]]*ApprovedTimeReport_001_202485[[#This Row],[Time Actual]] -> 191.66762 | T7: HUF do Brasil Ltda | U7: =VLOOKUP(A:A,Vlookup!A:B,2,0) -> FF
A8: 406-VCK498 | B8: 45524 | C8: 45538 | D8: SOW | E8: 2024 | F8: 8 | G8: 20 | H8: 34 | I8: 1 | J8: Sietech | K8: Nelson Simoes | L8: Program Manager | M8: Follow up de demandas de BPO. | N8: 157 | O8: =ApprovedTimeReport_001_202485[[#This Row],[CostRate]]/0.9075 -> 173.00275 | P8: =ApprovedTimeReport_001_202485[[#This Row],[CostRate (w/ Taxes)]]*ApprovedTimeReport_001_202485[[#This Row],[Time Actual]] -> 173.00275 | Q8: 195 | R8: =ApprovedTimeReport_001_202485[[#This Row],[BillingRate]]/0.8785 -> 221.96927 | S8: =ApprovedTimeReport_001_202485[[#This Row],[BillingRate w/ Taxes]]*ApprovedTimeReport_001_202485[[#This Row],[Time Actual]] -> 221.96927 | T8: Joyson safety System Brasil Ltda | U8: =VLOOKUP(A:A,Vlookup!A:B,2,0) -> FF
A9: 406-VCK498 | B9: 45518 | C9: 45538 | D9: SOW | E9: 2024 | F9: 8 | G9: 14 | H9: 33 | I9: 2 | J9: Sietech | K9: Nelson Simoes | L9: Program Manager | M9: Tratamento de demandas OD-322, 355, 394, 405 | N9: 157 | O9: =ApprovedTimeReport_001_202485[[#This Row],[CostRate]]/0.9075 -> 173.00275 | P9: =ApprovedTimeReport_001_202485[[#This Row],[CostRate (w/ Taxes)]]*ApprovedTimeReport_001_202485[[#This Row],[Time Actual]] -> 346.00551 | Q9: 195 | R9: =ApprovedTimeReport_001_202485[[#This Row],[BillingRate]]/0.8785 -> 221.96927 | S9: =ApprovedTimeReport_001_202485[[#This Row],[BillingRate w/ Taxes]]*ApprovedTimeReport_001_202485[[#This Row],[Time Actual]] -> 443.93853 | T9: Joyson safety System Brasil Ltda | U9: =VLOOKUP(A:A,Vlookup!A:B,2,0) -> FF
A10: NB-Consultoria-Tec&Dev | B10: 45534 | C10: 45538 | D10: NB01 | E10: 2024 | F10: 8 | G10: 30 | H10: 35 | I10: 8 | J10: Sietech | K10: Nelson Simoes | L10: Program Manager | M10: Preoparação de material para reunião gerencial, agenda de reunião gerencial, alinhamento com novos recursos de DEV, Mario e Marcos | N10: 99.83 | O10: 110 | P10: =ApprovedTimeReport_001_202485[[#This Row],[CostRate (w/ Taxes)]]*ApprovedTimeReport_001_202485[[#This Row],[Time Actual]] -> 880 | Q10: 0 | R10: =ApprovedTimeReport_001_202485[[#This Row],[BillingRate]]/0.8785 -> 0 | S10: =ApprovedTimeReport_001_202485[[#This Row],[BillingRate w/ Taxes]]*ApprovedTimeReport_001_202485[[#This Row],[Time Actual]] -> 0 | T10: Vockan Consulting Ltda | U10: =VLOOKUP(A:A,Vlookup!A:B,2,0) -> NB
A11: NB-Consultoria-Tec&Dev | B11: 45533 | C11: 45538 | D11: NB01 | E11: 2024 | F11: 8 | G11: 29 | H11: 35 | I11: 7 | J11: Sietech | K11: Nelson Simoes | L11: Program Manager | M11: Visita Joyson, follow up nova contratação dev, 5 candidatos | N11: 99.83 | O11: 110 | P11: =ApprovedTimeReport_001_202485[[#This Row],[CostRate (w/ Taxes)]]*ApprovedTimeReport_001_202485[[#This Row],[Time Actual]] -> 770 | Q11: 0 | R11: =ApprovedTimeReport_001_202485[[#This Row],[BillingRate]]/0.8785 -> 0 | S11: =ApprovedTimeReport_001_202485[[#This Row],[BillingRate w/ Taxes]]*ApprovedTimeReport_001_202485[[#This Row],[Time Actual]] -> 0 | T11: Vockan Consulting Ltda | U11: =VLOOKUP(A:A,Vlookup!A:B,2,0) -> NB
A12: NB-Consultoria-Tec&Dev | B12: 45532 | C12: 45538 | D12: NB01 | E12: 2024 | F12: 8 | G12: 28 | H12: 35 | I12: 5 | J12: Sietech | K12: Nelson Simoes | L12: Program Manager | M12: Reunião Visteon com Cristiano, alinhamento com PHL | N12: 99.83 | O12: 110 | P12: =ApprovedTimeReport_001_202485[[#This Row],[CostRate (w/ Taxes)]]*ApprovedTimeReport_001_202485[[#This Row],[Time Actual]] -> 550 | Q12: 0 | R12: =ApprovedTimeReport_001_202485[[#This Row],[BillingRate]]/0.8785 -> 0 | S12: =ApprovedTimeReport_001_202485[[#This Row],[BillingRate w/ Taxes]]*ApprovedTimeReport_001_202485[[#This Row],[Time Actual]] -> 0 | T12: Vockan Consulting Ltda | U12: =VLOOKUP(A:A,Vlookup!A:B,2,0) -> NB
A13: NB-Consultoria-Tec&Dev | B13: 45531 | C13: 45538 | D13: NB01 | E13: 2024 | F13: 8 | G13: 27 | H13: 35 | I13: 6 | J13: Sietech | K13: Nelson Simoes | L13: Program Manager | M13: Reunião com KYB, tratamento de proposta oxbo | N13: 99.83 | O13: 110 | P13: =ApprovedTimeReport_001_202485[[#This Row],[CostRate (w/ Taxes)]]*ApprovedTimeReport_001_202485[[#This Row],[Time Actual]] -> 660 | Q13: 0 | R13: =ApprovedTimeReport_001_202485[[#This Row],[BillingRate]]/0.8785 -> 0 | S13: =ApprovedTimeReport_001_202485[[#This Row],[BillingRate w/ Taxes]]*ApprovedTimeReport_001_202485[[#This Row],[Time Actual]] -> 0 | T13: Vockan Consulting Ltda | U13: =VLOOKUP(A:A,Vlookup!A:B,2,0) -> NB
A14: NB-Consultoria-Tec&Dev | B14: 45530 | C14: 45538 | D14: NB01 | E14: 2024 | F14: 8 | G14: 26 | H14: 35 | I14: 6 | J14: Sietech | K14: Nelson Simoes | L14: Program Manager | M14: Revisão de itens da sprint 13, alinhamento DEV, alinhamento Auto Kiniton e Amvac | N14: 99.83 | O14: 110 | P14: =ApprovedTimeReport_001_202485[[#This Row],[CostRate (w/ Taxes)]]*ApprovedTimeReport_001_202485[[#This Row],[Time Actual]] -> 660 | Q14: 0 | R14: =ApprovedTimeReport_001_202485[[#This Row],[BillingRate]]/0.8785 -> 0 | S14: =ApprovedTimeReport_001_202485[[#This Row],[BillingRate w/ Taxes]]*ApprovedTimeReport_001_202485[[#This Row],[Time Actual]] -> 0 | T14: Vockan Consulting Ltda | U14: =VLOOKUP(A:A,Vlookup!A:B,2,0) -> NB
A15: NB-Consultoria-Tec&Dev | B15: 45527 | C15: 45538 | D15: NB01 | E15: 2024 | F15: 8 | G15: 23 | H15: 34 | I15: 8 | J15: Sietech | K15: Nelson Simoes | L15: Program Manager | M15: fup tickets com Pedro, fup freudenberg com Fernanda, alinhamento de apresentação de cenário para HUF, alinhamento de back office com BPO | N15: 99.83 | O15: 110 | P15: =ApprovedTimeReport_001_202485[[#This Row],[CostRate (w/ Taxes)]]*ApprovedTimeReport_001_202485[[#This Row],[Time Actual]] -> 880 | Q15: 0 | R15: =ApprovedTimeReport_001_202485[[#This Row],[BillingRate]]/0.8785 -> 0 | S15: =ApprovedTimeReport_001_202485[[#This Row],[BillingRate w/ Taxes]]*ApprovedTimeReport_001_202485[[#This Row],[Time Actual]] -> 0 | T15: Vockan Consulting Ltda | U15: =VLOOKUP(A:A,Vlookup!A:B,2,0) -> NB
A16: NB-Consultoria-Tec&Dev | B16: 45526 | C16: 45538 | D16: NB01 | E16: 2024 | F16: 8 | G16: 22 | H16: 34 | I16: 8 | J16: Sietech | K16: Nelson Simoes | L16: Program Manager | M16: Alinhamento bpo operacional, minuta de contrato, alinhamento high business, scrum, reunião com projetos | N16: 99.83 | O16: 110 | P16: =ApprovedTimeReport_001_202485[[#This Row],[CostRate (w/ Taxes)]]*ApprovedTimeReport_001_202485[[#This Row],[Time Actual]] -> 880 | Q16: 0 | R16: =ApprovedTimeReport_001_202485[[#This Row],[BillingRate]]/0.8785 -> 0 | S16: =ApprovedTimeReport_001_202485[[#This Row],[BillingRate w/ Taxes]]*ApprovedTimeReport_001_202485[[#This Row],[Time Actual]] -> 0 | T16: Vockan Consulting Ltda | U16: =VLOOKUP(A:A,Vlookup!A:B,2,0) -> NB
A17: NB-Consultoria-Tec&Dev | B17: 45525 | C17: 45538 | D17: NB01 | E17: 2024 | F17: 8 | G17: 21 | H17: 34 | I17: 7 | J17: Sietech | K17: Nelson Simoes | L17: Program Manager | M17: Alionhamento Valmont, reunião TEC, Scrum | N17: 99.83 | O17: 110 | P17: =ApprovedTimeReport_001_202485[[#This Row],[CostRate (w/ Taxes)]]*ApprovedTimeReport_001_202485[[#This Row],[Time Actual]] -> 770 | Q17: 0 | R17: =ApprovedTimeReport_001_202485[[#This Row],[BillingRate]]/0.8785 -> 0 | S17: =ApprovedTimeReport_001_202485[[#This Row],[BillingRate w/ Taxes]]*ApprovedTimeReport_001_202485[[#This Row],[Time Actual]] -> 0 | T17: Vockan Consulting Ltda | U17: =VLOOKUP(A:A,Vlookup!A:B,2,0) -> NB
A18: NB-Consultoria-Tec&Dev | B18: 45524 | C18: 45538 | D18: NB01 | E18: 2024 | F18: 8 | G18: 20 | H18: 34 | I18: 6 | J18: Sietech | K18: Nelson Simoes | L18: Program Manager | M18: FUP comercial, bitrix, alinhamento TEC, Alinhamento DEV. | N18: 99.83 | O18: 110 | P18: =ApprovedTimeReport_001_202485[[#This Row],[CostRate (w/ Taxes)]]*ApprovedTimeReport_001_202485[[#This Row],[Time Actual]] -> 660 | Q18: 0 | R18: =ApprovedTimeReport_001_202485[[#This Row],[BillingRate]]/0.8785 -> 0 | S18: =ApprovedTimeReport_001_202485[[#This Row],[BillingRate w/ Taxes]]*ApprovedTimeReport_001_202485[[#This Row],[Time Actual]] -> 0 | T18: Vockan Consulting Ltda | U18: =VLOOKUP(A:A,Vlookup!A:B,2,0) -> NB
A19: NB-Consultoria-Tec&Dev | B19: 45523 | C19: 45538 | D19: NB01 | E19: 2024 | F19: 8 | G19: 19 | H19: 34 | I19: 4 | J19: Sietech | K19: Nelson Simoes | L19: Program Manager | M19: Scrum, tratamento de demandas de projeto com desenvolvimento. | N19: 99.83 | O19: 110 | P19: =ApprovedTimeReport_001_202485[[#This Row],[CostRate (w/ Taxes)]]*ApprovedTimeReport_001_202485[[#This Row],[Time Actual]] -> 440 | Q19: 0 | R19: =ApprovedTimeReport_001_202485[[#This Row],[BillingRate]]/0.8785 -> 0 | S19: =ApprovedTimeReport_001_202485[[#This Row],[BillingRate w/ Taxes]]*ApprovedTimeReport_001_202485[[#This Row],[Time Actual]] -> 0 | T19: Vockan Consulting Ltda | U19: =VLOOKUP(A:A,Vlookup!A:B,2,0) -> NB
A20: NB-Consultoria-Tec&Dev | B20: 45519 | C20: 45538 | D20: NB01 | E20: 2024 | F20: 8 | G20: 15 | H20: 33 | I20: 4 | J20: Sietech | K20: Nelson Simoes | L20: Program Manager | M20: Reunião com Cestari, alinhamento nova vaga desenvolvedor, scrum | N20: 99.83 | O20: 110 | P20: =ApprovedTimeReport_001_202485[[#This Row],[CostRate (w/ Taxes)]]*ApprovedTimeReport_001_202485[[#This Row],[Time Actual]] -> 440 | Q20: 0 | R20: =ApprovedTimeReport_001_202485[[#This Row],[BillingRate]]/0.8785 -> 0 | S20: =ApprovedTimeReport_001_202485[[#This Row],[BillingRate w/ Taxes]]*ApprovedTimeReport_001_202485[[#This Row],[Time Actual]] -> 0 | T20: Vockan Consulting Ltda | U20: =VLOOKUP(A:A,Vlookup!A:B,2,0) -> NB
A21: NB-Consultoria-Tec&Dev | B21: 45518 | C21: 45538 | D21: NB01 | E21: 2024 | F21: 8 | G21: 14 | H21: 33 | I21: 3 | J21: Sietech | K21: Nelson Simoes | L21: Program Manager | M21: Oportunidade comerciais, 1:1 André, alinhamento com Produtos | N21: 99.83 | O21: 110 | P21: =ApprovedTimeReport_001_202485[[#This Row],[CostRate (w/ Taxes)]]*ApprovedTimeReport_001_202485[[#This Row],[Time Actual]] -> 330 | Q21: 0 | R21: =ApprovedTimeReport_001_202485[[#This Row],[BillingRate]]/0.8785 -> 0 | S21: =ApprovedTimeReport_001_202485[[#This Row],[BillingRate w/ Taxes]]*ApprovedTimeReport_001_202485[[#This Row],[Time Actual]] -> 0 | T21: Vockan Consulting Ltda | U21: =VLOOKUP(A:A,Vlookup!A:B,2,0) -> NB
... A38: NBP-PE-PLAN12 | B38: 45520 | C38: 45538 | D38: SOW | E38: 2024 | F38: 8 | G38: 16 | H38: 33 | I38: 6 | J38: Sietech | K38: Nelson Simoes | L38: Project Manager | M38: Preparação de material comercial | N38: 99.83 | O38: 110 | P38: =ApprovedTimeReport_001_202485[[#This Row],[CostRate (w/ Taxes)]]*ApprovedTimeReport_001_202485[[#This Row],[Time Actual]] -> 660 | Q38: 0 | R38: =ApprovedTimeReport_001_202485[[#This Row],[BillingRate]]/0.8785 -> 0 | S38: =ApprovedTimeReport_001_202485[[#This Row],[BillingRate w/ Taxes]]*ApprovedTimeReport_001_202485[[#This Row],[Time Actual]] -> 0 | T38: Vockan Consulting Ltda | U38: =VLOOKUP(A:A,Vlookup!A:B,2,0) -> NB
A39: NBP-PE-PLAN23 | B39: 45505 | C39: 45538 | D39: SOW | E39: 2024 | F39: 8 | G39: 1 | H39: 31 | I39: 4 | J39: Sietech | K39: Nelson Simoes | L39: Project Manager | M39: Capacitação continuada com Exchange | N39: 157 | O39: =ApprovedTimeReport_001_202485[[#This Row],[CostRate]]/0.9075 -> 173.00275 | P39: =ApprovedTimeReport_001_202485[[#This Row],[CostRate (w/ Taxes)]]*ApprovedTimeReport_001_202485[[#This Row],[Time Actual]] -> 692.01102 | Q39: 0 | R39: =ApprovedTimeReport_001_202485[[#This Row],[BillingRate]]/0.8785 -> 0 | S39: =ApprovedTimeReport_001_202485[[#This Row],[BillingRate w/ Taxes]]*ApprovedTimeReport_001_202485[[#This Row],[Time Actual]] -> 0 | T39: Vockan Consulting Ltda | U39: =VLOOKUP(A:A,Vlookup!A:B,2,0) -> NB
A40: NB-Scrum-Dev | B40: 45532 | C40: 45538 | D40: SOW | E40: 2024 | F40: 8 | G40: 28 | H40: 35 | I40: 1 | J40: Sietech | K40: Nelson Simoes | L40: Program Manager | M40: planejamento sprint 14 | N40: 86.43 | O40: =ApprovedTimeReport_001_202485[[#This Row],[CostRate]]/0.9075 -> 95.239669 | P40: =ApprovedTimeReport_001_202485[[#This Row],[CostRate (w/ Taxes)]]*ApprovedTimeReport_001_202485[[#This Row],[Time Actual]] -> 95.239669 | Q40: 0 | R40: =ApprovedTimeReport_001_202485[[#This Row],[BillingRate]]/0.8785 -> 0 | S40: =ApprovedTimeReport_001_202485[[#This Row],[BillingRate w/ Taxes]]*ApprovedTimeReport_001_202485[[#This Row],[Time Actual]] -> 0 | T40: Vockan Consulting Ltda | U40: =VLOOKUP(A:A,Vlookup!A:B,2,0) -> NB
A41: NB-Scrum-Dev | B41: 45531 | C41: 45538 | D41: SOW | E41: 2024 | F41: 8 | G41: 27 | H41: 35 | I41: 1 | J41: Sietech | K41: Nelson Simoes | L41: Program Manager | M41: fechamento Sprint 13 | N41: 86.43 | O41: =ApprovedTimeReport_001_202485[[#This Row],[CostRate]]/0.9075 -> 95.239669 | P41: =ApprovedTimeReport_001_202485[[#This Row],[CostRate (w/ Taxes)]]*ApprovedTimeReport_001_202485[[#This Row],[Time Actual]] -> 95.239669 | Q41: 0 | R41: =ApprovedTimeReport_001_202485[[#This Row],[BillingRate]]/0.8785 -> 0 | S41: =ApprovedTimeReport_001_202485[[#This Row],[BillingRate w/ Taxes]]*ApprovedTimeReport_001_202485[[#This Row],[Time Actual]] -> 0 | T41: Vockan Consulting Ltda | U41: =VLOOKUP(A:A,Vlookup!A:B,2,0) -> NB
A42: NB-Scrum-Dev | B42: 45518 | C42: 45538 | D42: SOW | E42: 2024 | F42: 8 | G42: 14 | H42: 33 | I42: 1 | J42: Sietech | K42: Nelson Simoes | L42: Program Manager | M42: planejamento sprint 13 | N42: 86.43 | O42: =ApprovedTimeReport_001_202485[[#This Row],[CostRate]]/0.9075 -> 95.239669 | P42: =ApprovedTimeReport_001_202485[[#This Row],[CostRate (w/ Taxes)]]*ApprovedTimeReport_001_202485[[#This Row],[Time Actual]] -> 95.239669 | Q42: 0 | R42: =ApprovedTimeReport_001_202485[[#This Row],[BillingRate]]/0.8785 -> 0 | S42: =ApprovedTimeReport_001_202485[[#This Row],[BillingRate w/ Taxes]]*ApprovedTimeReport_001_202485[[#This Row],[Time Actual]] -> 0 | T42: Vockan Consulting Ltda | U42: =VLOOKUP(A:A,Vlookup!A:B,2,0) -> NB
A43: NB-Scrum-Dev | B43: 45517 | C43: 45538 | D43: SOW | E43: 2024 | F43: 8 | G43: 13 | H43: 33 | I43: 1 | J43: Sietech | K43: Nelson Simoes | L43: Program Manager | M43: fechamento sprint 12 | N43: 86.43 | O43: =ApprovedTimeReport_001_202485[[#This Row],[CostRate]]/0.9075 -> 95.239669 | P43: =ApprovedTimeReport_001_202485[[#This Row],[CostRate (w/ Taxes)]]*ApprovedTimeReport_001_202485[[#This Row],[Time Actual]] -> 95.239669 | Q43: 0 | R43: =ApprovedTimeReport_001_202485[[#This Row],[BillingRate]]/0.8785 -> 0 | S43: =ApprovedTimeReport_001_202485[[#This Row],[BillingRate w/ Taxes]]*ApprovedTimeReport_001_202485[[#This Row],[Time Actual]] -> 0 | T43: Vockan Consulting Ltda | U43: =VLOOKUP(A:A,Vlookup!A:B,2,0) -> NB

Sheet Vlookup
A1: FunnelID | B1: Project Type
A2: 074-Vckadi | B2: FF
A3: 095-vckadi | B3: FF
A4: 128-VckAdi | B4: FF
A5: 806-Vck446 | B5: FF
A6: NB-Support | B6: NB
A7: 049-VckAmv | B7: FF
A8: 089-vckand | B8: FF
A9: A7lAPT28665 | B9: FF
A10: 131-VckAut | B10: T&M
A11: 010-VckBim | B11: T&M
A12: 068-vckcar | B12: T&M
... A96: 976-VCK510 | B96: T&M
