Workbook

Sheet Summary
A3: Rótulos de Linha | B3: Project Type | C3: Resource Name | D3: FunnelID | E3: CostRate w/ Taxes | F3: Soma de Time Actual | G3: Soma de Total Cost
A4: Sietech | B4: FF | C4: Nelson Simoes | D4: 4328-VCK1760 | E4: 173.00275 | F4: 2 | G4: 346.00551
D5: 448-VCK494 | E5: 173.00275 | F5: 1 | G5: 173.00275
D6: 4522-VCK452 | E6: 173.00275 | F6: 6 | G6: 1038.0165
D7: 458-VCK492 | E7: 173.00275 | F7: 1 | G7: 173.00275
D8: 8168-VCK514 | E8: 173.00275 | F8: 1 | G8: 173.00275
B9: FF Total | F9: 11 | G9: 1903.0303 | H9: BRP2564
B10: NB | C10: Nelson Simoes | D10: NB-BITRIX | E10: 110 | F10: 9 | G10: 990
D11: NB-BPO e PMO | E11: 110 | F11: 80 | G11: 8800
D12: NB-Consultoria-Tec&Dev | E12: 110 | F12: 59 | G12: 6490
D13: NBP-PE-PLAN12 | E13: 110 | F13: 4 | G13: 440
D14: NBP-PEVO97 | E14: 110 | F14: 8 | G14: 880
B15: NB Total | F15: 160 | G15: 17600 | H15: BRP2565
B16: T&M | C16: Nelson Simoes | D16: 876-VCK490 | E16: 173.00275 | F16: 1 | G16: 173.00275
B17: T&M Total | F17: 1 | G17: 173.00275 | H17: BRP2566
A18: Sietech Total | F18: 172 | G18: 19676.033
A19: Total Geral | F19: 172 | G19: 19676.033

Sheet Marco 2025
A1: FunnelID | B1: Work Date | C1: Date TimeSheet | D1: CCID | E1: Year | F1: Month | G1: Day | H1: Week | I1: Time Actual | J1: Company | K1: Resource Name | L1: Role | M1: Comments | N1: CostRate | O1: CostRate w/ Taxes | P1: Total Cost | Q1: Customer Name | R1: Project Type
A2: 4522-VCK452 | B2: 45722 | C2: 45726 | D2: SOW | E2: 2025 | F2: 3 | G2: 6 | H2: 10 | I2: 1 | J2: Sietech | K2: Nelson Simoes | L2: Project Manager | M2: Alinhamento com toda equipe funcional e dev envolvida no backlog aptiv | N2: 157 | O2: =ApprovedTimeReport_007_202534[[#This Row],[CostRate]]/0.9075 -> 173.00275 | P2: =ApprovedTimeReport_007_202534[[#This Row],[CostRate w/ Taxes]]*ApprovedTimeReport_007_202534[[#This Row],[Time Actual]] -> 173.00275 | Q2: APTIV Man e Serv de Distr. Ltda | R2: =VLOOKUP(A:A,Vlookup!A:B,2,0) -> FF
A3: 4522-VCK452 | B3: 45721 | C3: 45726 | D3: SOW | E3: 2025 | F3: 3 | G3: 5 | H3: 10 | I3: 1 | J3: Sietech | K3: Nelson Simoes | L3: Project Manager | M3: Alinhamento de volume contratual | N3: 157 | O3: =ApprovedTimeReport_007_202534[[#This Row],[CostRate]]/0.9075 -> 173.00275 | P3: =ApprovedTimeReport_007_202534[[#This Row],[CostRate w/ Taxes]]*ApprovedTimeReport_007_202534[[#This Row],[Time Actual]] -> 173.00275 | Q3: APTIV Man e Serv de Distr. Ltda | R3: =VLOOKUP(A:A,Vlookup!A:B,2,0) -> FF
A4: 4522-VCK452 | B4: 45719 | C4: 45726 | D4: SOW | E4: 2025 | F4: 3 | G4: 3 | H4: 10 | I4: 2 | J4: Sietech | K4: Nelson Simoes | L4: Project Manager | M4: Plano de trabalho para quitação de backlog | N4: 157 | O4: =ApprovedTimeReport_007_202534[[#This Row],[CostRate]]/0.9075 -> 173.00275 | P4: =ApprovedTimeReport_007_202534[[#This Row],[CostRate w/ Taxes]]*ApprovedTimeReport_007_202534[[#This Row],[Time Actual]] -> 346.00551 | Q4: APTIV Man e Serv de Distr. Ltda | R4: =VLOOKUP(A:A,Vlookup!A:B,2,0) -> FF
A5: 4522-VCK452 | B5: 45729 | C5: 45733 | D5: SOW | E5: 2025 | F5: 3 | G5: 13 | H5: 11 | I5: 2 | J5: Sietech | K5: Nelson Simoes | L5: Project Manager | M5: Praparação de material para reunião presencial e alinhamento com time sobre back log, dev e BPO | N5: 157 | O5: =ApprovedTimeReport_007_202534[[#This Row],[CostRate]]/0.9075 -> 173.00275 | P5: =ApprovedTimeReport_007_202534[[#This Row],[CostRate w/ Taxes]]*ApprovedTimeReport_007_202534[[#This Row],[Time Actual]] -> 346.00551 | Q5: APTIV Man e Serv de Distr. Ltda | R5: =VLOOKUP(A:A,Vlookup!A:B,2,0) -> FF
A6: 876-VCK490 | B6: 45735 | C6: 45740 | D6: SOW | E6: 2025 | F6: 3 | G6: 19 | H6: 12 | I6: 1 | J6: Sietech | K6: Nelson Simoes | L6: Project Manager | M6: Alinhamento de demandas Freud com Parrillo. | N6: 157 | O6: =ApprovedTimeReport_007_202534[[#This Row],[CostRate]]/0.9075 -> 173.00275 | P6: =ApprovedTimeReport_007_202534[[#This Row],[CostRate w/ Taxes]]*ApprovedTimeReport_007_202534[[#This Row],[Time Actual]] -> 173.00275 | Q6: Freudenberg Nok Comp Br Ltd | R6: =VLOOKUP(A:A,Vlookup!A:B,2,0) -> T&M
A7: 458-VCK492 | B7: 45728 | C7: 45733 | D7: SOW | E7: 2025 | F7: 3 | G7: 12 | H7: 11 | I7: 1 | J7: Sietech | K7: Nelson Simoes | L7: Project Manager | M7: Alinhamento sobre pacotes para conversão | N7: 157 | O7: =ApprovedTimeReport_007_202534[[#This Row],[CostRate]]/0.9075 -> 173.00275 | P7: =ApprovedTimeReport_007_202534[[#This Row],[CostRate w/ Taxes]]*ApprovedTimeReport_007_202534[[#This Row],[Time Actual]] -> 173.00275 | Q7: Hanon Systems Climatizacao Do | R7: =VLOOKUP(A:A,Vlookup!A:B,2,0) -> FF
A8: 448-VCK494 | B8: 45729 | C8: 45733 | D8: SOW | E8: 2025 | F8: 3 | G8: 13 | H8: 11 | I8: 1 | J8: Sietech | K8: Nelson Simoes | L8: Program Manager | M8: Alinhamento sobre scan de customizados com Parpinelli | N8: 157 | O8: =ApprovedTimeReport_007_202534[[#This Row],[CostRate]]/0.9075 -> 173.00275 | P8: =ApprovedTimeReport_007_202534[[#This Row],[CostRate w/ Taxes]]*ApprovedTimeReport_007_202534[[#This Row],[Time Actual]] -> 173.00275 | Q8: HUF do Brasil Ltda | R8: =VLOOKUP(A:A,Vlookup!A:B,2,0) -> FF
A9: 8168-VCK514 | B9: 45743 | C9: 45747 | D9: SOW | E9: 2025 | F9: 3 | G9: 27 | H9: 13 | I9: 1 | J9: Sietech | K9: Nelson Simoes | L9: Project Manager | M9: Alinhamento de demandas de BPO | N9: 157 | O9: =ApprovedTimeReport_007_202534[[#This Row],[CostRate]]/0.9075 -> 173.00275 | P9: =ApprovedTimeReport_007_202534[[#This Row],[CostRate w/ Taxes]]*ApprovedTimeReport_007_202534[[#This Row],[Time Actual]] -> 173.00275 | Q9: OXBO DO BRASIL EQUIPAMENTOS | R9: =VLOOKUP(A:A,Vlookup!A:B,2,0) -> FF
A10: NB-BITRIX | B10: 45719 | C10: 45726 | D10: SOW | E10: 2025 | F10: 3 | G10: 3 | H10: 10 | I10: 1 | J10: Sietech | K10: Nelson Simoes | L10: Project Manager | M10: Atualização Bitrix | N10: 99.83 | O10: 110 | P10: =ApprovedTimeReport_007_202534[[#This Row],[CostRate w/ Taxes]]*ApprovedTimeReport_007_202534[[#This Row],[Time Actual]] -> 110 | Q10: Vockan Consulting Ltda | R10: =VLOOKUP(A:A,Vlookup!A:B,2,0) -> NB
A11: NB-BITRIX | B11: 45729 | C11: 45733 | D11: SOW | E11: 2025 | F11: 3 | G11: 13 | H11: 11 | I11: 1 | J11: Sietech | K11: Nelson Simoes | L11: Project Manager | M11: Atualização de cards | N11: 99.83 | O11: 110 | P11: =ApprovedTimeReport_007_202534[[#This Row],[CostRate w/ Taxes]]*ApprovedTimeReport_007_202534[[#This Row],[Time Actual]] -> 110 | Q11: Vockan Consulting Ltda | R11: =VLOOKUP(A:A,Vlookup!A:B,2,0) -> NB
A12: NB-BITRIX | B12: 45722 | C12: 45726 | D12: SOW | E12: 2025 | F12: 3 | G12: 6 | H12: 10 | I12: 1 | J12: Sietech | K12: Nelson Simoes | L12: Project Manager | M12: Atualização de cards Bitrix | N12: 99.83 | O12: 110 | P12: =ApprovedTimeReport_007_202534[[#This Row],[CostRate w/ Taxes]]*ApprovedTimeReport_007_202534[[#This Row],[Time Actual]] -> 110 | Q12: Vockan Consulting Ltda | R12: =VLOOKUP(A:A,Vlookup!A:B,2,0) -> NB
A13: NB-BITRIX | B13: 45730 | C13: 45733 | D13: SOW | E13: 2025 | F13: 3 | G13: 14 | H13: 11 | I13: 2 | J13: Sietech | K13: Nelson Simoes | L13: Project Manager | M13: Atualização de cards e planilha de resumo | N13: 99.83 | O13: 110 | P13: =ApprovedTimeReport_007_202534[[#This Row],[CostRate w/ Taxes]]*ApprovedTimeReport_007_202534[[#This Row],[Time Actual]] -> 220 | Q13: Vockan Consulting Ltda | R13: =VLOOKUP(A:A,Vlookup!A:B,2,0) -> NB
A14: NB-BITRIX | B14: 45723 | C14: 45726 | D14: SOW | E14: 2025 | F14: 3 | G14: 7 | H14: 10 | I14: 1 | J14: Sietech | K14: Nelson Simoes | L14: Project Manager | M14: Atualização de planilha YTD | N14: 99.83 | O14: 110 | P14: =ApprovedTimeReport_007_202534[[#This Row],[CostRate w/ Taxes]]*ApprovedTimeReport_007_202534[[#This Row],[Time Actual]] -> 110 | Q14: Vockan Consulting Ltda | R14: =VLOOKUP(A:A,Vlookup!A:B,2,0) -> NB
A15: NB-BITRIX | B15: 45735 | C15: 45740 | D15: SOW | E15: 2025 | F15: 3 | G15: 19 | H15: 12 | I15: 1 | J15: Sietech | K15: Nelson Simoes | L15: Project Manager | M15: Fup Bitrix | N15: 99.83 | O15: 110 | P15: =ApprovedTimeReport_007_202534[[#This Row],[CostRate w/ Taxes]]*ApprovedTimeReport_007_202534[[#This Row],[Time Actual]] -> 110 | Q15: Vockan Consulting Ltda | R15: =VLOOKUP(A:A,Vlookup!A:B,2,0) -> NB
A16: NB-BITRIX | B16: 45742 | C16: 45747 | D16: SOW | E16: 2025 | F16: 3 | G16: 26 | H16: 13 | I16: 2 | J16: Sietech | K16: Nelson Simoes | L16: Project Manager | M16: FUP Bitrix e reunião com diretores para report | N16: 99.83 | O16: 110 | P16: =ApprovedTimeReport_007_202534[[#This Row],[CostRate w/ Taxes]]*ApprovedTimeReport_007_202534[[#This Row],[Time Actual]] -> 220 | Q16: Vockan Consulting Ltda | R16: =VLOOKUP(A:A,Vlookup!A:B,2,0) -> NB
A17: NB-BPO e PMO | B17: 45728 | C17: 45733 | D17: CO01 | E17: 2025 | F17: 3 | G17: 12 | H17: 11 | I17: 1 | J17: Sietech | K17: Nelson Simoes | L17: Project Manager | M17: Alinhamento Aptiv | N17: 99.83 | O17: 110 | P17: =ApprovedTimeReport_007_202534[[#This Row],[CostRate w/ Taxes]]*ApprovedTimeReport_007_202534[[#This Row],[Time Actual]] -> 110 | Q17: Vockan Consulting Ltda | R17: =VLOOKUP(A:A,Vlookup!A:B,2,0) -> NB
A18: NB-BPO e PMO | B18: 45733 | C18: 45740 | D18: CO01 | E18: 2025 | F18: 3 | G18: 17 | H18: 12 | I18: 2 | J18: Sietech | K18: Nelson Simoes | L18: Project Manager | M18: Alinhamento com Daniel e Guilherme, checkpoint Aptiv | N18: 99.83 | O18: 110 | P18: =ApprovedTimeReport_007_202534[[#This Row],[CostRate w/ Taxes]]*ApprovedTimeReport_007_202534[[#This Row],[Time Actual]] -> 220 | Q18: Vockan Consulting Ltda | R18: =VLOOKUP(A:A,Vlookup!A:B,2,0) -> NB
A19: NB-BPO e PMO | B19: 45721 | C19: 45726 | D19: CO01 | E19: 2025 | F19: 3 | G19: 5 | H19: 10 | I19: 3 | J19: Sietech | K19: Nelson Simoes | L19: Project Manager | M19: Alinhamento com Fábio, Fup oportunidades, atualização de propostas | N19: 99.83 | O19: 110 | P19: =ApprovedTimeReport_007_202534[[#This Row],[CostRate w/ Taxes]]*ApprovedTimeReport_007_202534[[#This Row],[Time Actual]] -> 330 | Q19: Vockan Consulting Ltda | R19: =VLOOKUP(A:A,Vlookup!A:B,2,0) -> NB
A20: NB-BPO e PMO | B20: 45742 | C20: 45747 | D20: CO01 | E20: 2025 | F20: 3 | G20: 26 | H20: 13 | I20: 3 | J20: Sietech | K20: Nelson Simoes | L20: Project Manager | M20: Alinhamento com Pamela, taskforce Aptiv, reunião KYB, alinhamento com Fábio | N20: 99.83 | O20: 110 | P20: =ApprovedTimeReport_007_202534[[#This Row],[CostRate w/ Taxes]]*ApprovedTimeReport_007_202534[[#This Row],[Time Actual]] -> 330 | Q20: Vockan Consulting Ltda | R20: =VLOOKUP(A:A,Vlookup!A:B,2,0) -> NB
A21: NB-BPO e PMO | B21: 45723 | C21: 45726 | D21: CO01 | E21: 2025 | F21: 3 | G21: 7 | H21: 10 | I21: 8 | J21: Sietech | K21: Nelson Simoes | L21: Project Manager | M21: Alinhamento HUF, plano de trabalho de medição de produtividade, SLA dinâmico , pagamento fracionado de demandas, reunião com Aptiv para fechamento de escopo de taskforce | N21: 99.83 | O21: 110 | P21: =ApprovedTimeReport_007_202534[[#This Row],[CostRate w/ Taxes]]*ApprovedTimeReport_007_202534[[#This Row],[Time Actual]] -> 880 | Q21: Vockan Consulting Ltda | R21: =VLOOKUP(A:A,Vlookup!A:B,2,0) -> NB
... A53: NBP-PEVO97 | B53: 45741 | C53: 45747 | D53: SOW | E53: 2025 | F53: 3 | G53: 25 | H53: 13 | I53: 8 | J53: Sietech | K53: Nelson Simoes | L53: Project Manager | M53: Participação no Summit, dia inteiro, 8h as 16h | N53: 99.83 | O53: 110 | P53: =ApprovedTimeReport_007_202534[[#This Row],[CostRate w/ Taxes]]*ApprovedTimeReport_007_202534[[#This Row],[Time Actual]] -> 880 | Q53: Vockan Consulting Ltda | R53: =VLOOKUP(A:A,Vlookup!A:B,2,0) -> NB
A54: 4328-VCK1760 | B54: 45726 | C54: 45733 | D54: SOW | E54: 2025 | F54: 3 | G54: 10 | H54: 11 | I54: 2 | J54: Sietech | K54: Nelson Simoes | L54: Project Manager | M54: Alinhamento de demandas com Leopoldo e com equipe | N54: 157 | O54: =ApprovedTimeReport_007_202534[[#This Row],[CostRate]]/0.9075 -> 173.00275 | P54: =ApprovedTimeReport_007_202534[[#This Row],[CostRate w/ Taxes]]*ApprovedTimeReport_007_202534[[#This Row],[Time Actual]] -> 346.00551 | Q54: ZF Passive Safety System Brazil Ltda | R54: =VLOOKUP(A:A,Vlookup!A:B,2,0) -> FF

Sheet Vlookup
A1: FunnelID | B1: Project Type
A2: 074-Vckadi | B2: FF
A3: 095-vckadi | B3: FF
A4: 128-VckAdi | B4: FF
A5: 806-Vck446 | B5: FF
A6: NB-Support | B6: NB
A7: 049-VckAmv | B7: FF
A8: 089-vckand | B8: FF
A9: A7lAPT28665 | B9: FF
A10: 131-VckAut | B10: T&M
A11: 010-VckBim | B11: T&M
A12: 068-vckcar | B12: T&M
... A148: 872-VCK514 | B148: FF
